etornado/__init__.py
etornado/application.py
etornado/error_code_manager.py
etornado/buildin_handlers/__init__.py
etornado/buildin_handlers/base_handler.py
etornado/buildin_handlers/logging_handler.py
etornado/buildin_handlers/unsupported_url_handler.py
etornado-0.1.16.dist-info/METADATA
etornado-0.1.16.dist-info/WHEEL
etornado-0.1.16.dist-info/top_level.txt
etornado-0.1.16.dist-info/RECORD
