Metadata-Version: 2.1
Name: etornado
Version: 0.1.16
Summary: a wrapper for tornado
Home-page: UNKNOWN
Author: sheng_xc
Author-email: sheng_xc@126.com
License: UNKNOWN
Platform: UNKNOWN
Classifier: Programming Language :: Python :: 3
Classifier: License :: OSI Approved :: MIT License
Classifier: Operating System :: OS Independent
Requires-Python: >=3.5
Requires-Dist: tornado (==6.0.3)
Requires-Dist: etools (>=0.0.10)
